studio/__init__.py
studio/apiserver.py
studio/apiserver_config.yaml
studio/app.yaml
studio/appengine_config.py
studio/artifact.py
studio/artifact_store.py
studio/auth.py
studio/base_artifact_store.py
studio/cli.py
studio/client_config.yaml
studio/cloud_worker_util.py
studio/credentials.py
studio/default_config.yaml
studio/dependencies_policy.py
studio/deploy_apiserver.sh
studio/ec2cloud_worker.py
studio/ed25519_key_util.py
studio/encrypted_payload_builder.py
studio/experiment.py
studio/experiment_submitter.py
studio/extra_util.py
studio/firebase_artifact_store.py
studio/firebase_provider.py
studio/firebase_storage_handler.py
studio/fs_tracker.py
studio/gcloud_artifact_store.py
studio/gcloud_worker.py
studio/git_util.py
studio/gpu_util.py
studio/gs_provider.py
studio/http_artifact_store.py
studio/http_provider.py
studio/http_storage_handler.py
studio/hyperparameter.py
studio/keyvalue_provider.py
studio/local_artifact_store.py
studio/local_db_provider.py
studio/local_queue.py
studio/local_storage_handler.py
studio/local_worker.py
studio/logs.py
studio/magics.py
studio/model.py
studio/model_setup.py
studio/model_util.py
studio/multi_gpu.py
studio/payload_builder.py
studio/postgres_provider.py
studio/pubsub_queue.py
studio/pyrebase.py
studio/qclient_cache.py
studio/rabbit_queue.py
studio/remote_worker.py
studio/rmq_config.yml
studio/run_magic.py.stub
studio/runner.py
studio/s3_artifact_store.py
studio/s3_provider.py
studio/s3_storage_handler.py
studio/serve.py
studio/serve_main.py
studio/server_config.yaml
studio/sqs_queue.py
studio/storage_handler.py
studio/storage_handler_factory.py
studio/storage_type.py
studio/storage_util.py
studio/studio_dependencies_policy.py
studio/tartifact_store.py
studio/unencrypted_payload_builder.py
studio/util.py
studio/artifacts/__init__.py
studio/artifacts/artifact.py
studio/artifacts/artifacts_tracker.py
studio/aws/aws_amis.yaml
studio/aws/aws_prices.yaml
studio/completion_service/__init__.py
studioml-0.0.49.dist-info/LICENSE
studioml-0.0.49.dist-info/METADATA
studioml-0.0.49.dist-info/WHEEL
studioml-0.0.49.dist-info/top_level.txt
studioml-0.0.49.dist-info/RECORD
