Metadata-Version: 2.1
Name: studioml
Version: 0.0.49
Summary: TensorFlow model and data management tool
Home-page: https://github.com/studioml/studio
Author: Illia Polosukhin
Author-email: illia.polosukhin@gmail.com
License: Apache License, Version 2.0
Keywords: TensorFlow studioml StudioML Studio Keras scikit-learn
Platform: UNKNOWN
Classifier: Development Status :: 4 - Beta
Classifier: Environment :: Console
Classifier: Intended Audience :: Developers
Classifier: Intended Audience :: Science/Research
Classifier: Operating System :: POSIX :: Linux
Classifier: Programming Language :: Python :: 3.6
Classifier: Topic :: Scientific/Engineering :: Artificial Intelligence
Classifier: Topic :: Utilities
Classifier: License :: OSI Approved :: Apache Software License
Requires-Python: >=3.4
Requires-Dist: pip
Requires-Dist: setuptools-scm
Requires-Dist: setuptools-scm-git-archive
Requires-Dist: configparser
Requires-Dist: numpy
Requires-Dist: flask
Requires-Dist: cma
Requires-Dist: psutil
Requires-Dist: apscheduler
Requires-Dist: openssh-key-parser
Requires-Dist: pycryptodome
Requires-Dist: sshpubkeys
Requires-Dist: PyNaCl
Requires-Dist: requests
Requires-Dist: requests-toolbelt
Requires-Dist: python-jwt
Requires-Dist: sseclient
Requires-Dist: terminaltables
Requires-Dist: PyYAML
Requires-Dist: pyhocon
Requires-Dist: google-api-core
Requires-Dist: google-api-python-client
Requires-Dist: google-cloud-storage
Requires-Dist: google-cloud-pubsub
Requires-Dist: google-auth-httplib2
Requires-Dist: oauth2client (==3.0.0)
Requires-Dist: boto3
Requires-Dist: rsa
Requires-Dist: filelock
Requires-Dist: pika (>=1.1.0)
